docking/__init__.py
docking/__main__.py
tests/__init__.py
tests/__main__.py
docking-0.0.1.dist-info/METADATA
docking-0.0.1.dist-info/WHEEL
docking-0.0.1.dist-info/entry_points.txt
docking-0.0.1.dist-info/top_level.txt
docking-0.0.1.dist-info/RECORD
